168x_cua-0.1.12.dist-info/licenses/LICENSE
cua/config.py
cua/main.py
cua/settings.py
cua/state.py
cua/utils.py
cua/ai/client.py
cua/ai/loop.py
cua/ai/mainloop.py
cua/ai/tool_box.py
cua/ai/llm_request_builder/anthropic_request_builder.py
cua/ai/llm_request_builder/base_request_builder.py
cua/ai/tools/computer_use.py
cua/ai/tools/linkedin_crustdata.py
cua/ai/tools/memory.py
cua/ai/tools/subagent.py
cua/ai/tools/subagent_legacy.py
cua/db/database.py
cua/db/models.py
cua/logging/logging_config_dev.py
cua/logging/logging_config_windows.py
cua/services/events.py
cua_protocol/__init__.py
cua_protocol/schemas.py
168x_cua-0.1.12.dist-info/METADATA
168x_cua-0.1.12.dist-info/WHEEL
168x_cua-0.1.12.dist-info/entry_points.txt
168x_cua-0.1.12.dist-info/top_level.txt
168x_cua-0.1.12.dist-info/RECORD
